virtual_allocator/__init__.py
virtual_allocator-0.0.3.dist-info/METADATA
virtual_allocator-0.0.3.dist-info/WHEEL
virtual_allocator-0.0.3.dist-info/licenses/LICENSE
virtual_allocator-0.0.3.dist-info/RECORD
