Metadata-Version: 2.4
Name: virtual-allocator
Version: 0.0.3
Summary: Python allocator for a virtual memory range
Project-URL: Homepage, https://github.com/jonasehrlich/virtual-allocator
Project-URL: Repository, https://github.com/jonasehrlich/virtual-allocator
Author-email: Jonas Ehrlich <jonas.ehrlich@gmail.com>
License: MIT
License-File: LICENSE
Keywords: allocator,memory
Classifier: Development Status :: 3 - Alpha
Classifier: Environment :: Console
Classifier: License :: OSI Approved :: MIT License
Classifier: Operating System :: OS Independent
Classifier: Programming Language :: Python
Requires-Python: >=3.11
